LICENSE
MANIFEST.in
README.md
bautils.py
setup.py
bautils.egg-info/PKG-INFO
bautils.egg-info/SOURCES.txt
bautils.egg-info/dependency_links.txt
bautils.egg-info/requires.txt
bautils.egg-info/top_level.txt
tests/__init__.py
tests/bautils_test.py
tests/converter_test.py