Metadata-Version: 1.1
Name: bautils
Version: 0.1.1
Summary: Utils for the Python bitarray module
Home-page: https://gitlab.com/TC01/python-bautils
Author: Ben Rosser
Author-email: rosser.bjr@gmail.com
License: MIT
Keywords: bitarray binary bitstring
Platform: UNKNOWN
Classifier: Development Status :: 3 - Alpha
Classifier: Intended Audience :: Developers
Classifier: Intended Audience :: Science/Research
Classifier: License :: OSI Approved :: MIT License
Classifier: Programming Language :: Python :: 2
Classifier: Programming Language :: Python :: 2.7
Classifier: Programming Language :: Python :: 3
Classifier: Programming Language :: Python :: 3.3
Classifier: Programming Language :: Python :: 3.4
Classifier: Programming Language :: Python :: 3.5
